based/__init__.py
based/database.py
based/errors.py
based/py.typed
based/backends/__init__.py
based/backends/mysql.py
based/backends/postgresql.py
based/backends/sqlite.py
based-0.7.0.dist-info/LICENSE.txt
based-0.7.0.dist-info/METADATA
based-0.7.0.dist-info/WHEEL
based-0.7.0.dist-info/top_level.txt
based-0.7.0.dist-info/RECORD
