Metadata-Version: 2.1
Name: based
Version: 0.7.0
Summary: A based asynchronous database connection manager.
Author-email: ansipunk <kysput@gmail.com>
License: MIT License
Project-URL: Homepage, https://github.com/ansipunk/based
Project-URL: Repository, https://github.com/ansipunk/based.git
Project-URL: Issues, https://github.com/ansipunk/based/issues
Keywords: database,sqlalchemy,sqlite,asyncio,postgresql,mysql
Classifier: Development Status :: 3 - Alpha
Classifier: Topic :: Database
Classifier: Environment :: Web Environment
Classifier: Intended Audience :: Developers
Classifier: License :: OSI Approved :: MIT License
Classifier: Programming Language :: Python :: 3
Classifier: Programming Language :: Python :: 3.8
Classifier: Programming Language :: Python :: 3.9
Classifier: Programming Language :: Python :: 3.10
Classifier: Programming Language :: Python :: 3.11
Classifier: Programming Language :: Python :: 3.12
Classifier: Programming Language :: Python :: 3.13
Requires-Python: >=3.8
License-File: LICENSE.txt
Requires-Dist: SQLAlchemy <2.1,>=2
Provides-Extra: dev
Requires-Dist: mysqlclient <3,>=2.2 ; extra == 'dev'
Requires-Dist: psycopg2-binary <3,>=2.9 ; extra == 'dev'
Requires-Dist: pytest <9,>=8 ; extra == 'dev'
Requires-Dist: pytest-asyncio <1,>=0.24 ; extra == 'dev'
Requires-Dist: pytest-cov <6,>=5 ; extra == 'dev'
Requires-Dist: pytest-mock <4,>=3 ; extra == 'dev'
Requires-Dist: pytest-xdist <4,>=3 ; extra == 'dev'
Requires-Dist: ruff <0.8,>=0.7 ; extra == 'dev'
Requires-Dist: SQLAlchemy-Utils <1,>=0.41 ; extra == 'dev'
Provides-Extra: mysql
Requires-Dist: asyncmy <1,>=0.2 ; extra == 'mysql'
Provides-Extra: postgres
Requires-Dist: psycopg <4,>=3 ; extra == 'postgres'
Requires-Dist: psycopg-pool <4,>=3 ; extra == 'postgres'
Provides-Extra: sqlite
Requires-Dist: aiosqlite <1,>=0.20 ; extra == 'sqlite'
